AFMReader/__init__.py
AFMReader/_version.py
AFMReader/asd.py
AFMReader/default_config.yaml
AFMReader/general_loader.py
AFMReader/gwy.py
AFMReader/h5_jpk.py
AFMReader/ibw.py
AFMReader/io.py
AFMReader/jpk.py
AFMReader/logging.py
AFMReader/spm.py
AFMReader/stp.py
AFMReader/top.py
AFMReader/topostats.py
afmreader-0.0.7.dist-info/licenses/COPYING
afmreader-0.0.7.dist-info/METADATA
afmreader-0.0.7.dist-info/WHEEL
afmreader-0.0.7.dist-info/top_level.txt
afmreader-0.0.7.dist-info/RECORD
