Metadata-Version: 2.4
Name: AFMReader
Version: 0.0.7
Summary: Read and retrieve data from various AFM file formats.
Author-email: Sylvia Whittle <sylvia.whittle@sheffield.ac.uk>, Neil Shephard <n.shephard@sheffield.ac.uk>, TopoStats Team <topostats@sheffield.ac.uk>
Project-URL: Homepage, https://github.com/AFM-SPM/afmreader
Project-URL: Bug Tracker, https://github.com/AFM-SPM/afmreader/issues
Keywords: afm,image processing
Classifier: Development Status :: 3 - Alpha
Classifier: License :: OSI Approved :: GNU Lesser General Public License v3 (LGPLv3)
Classifier: Natural Language :: English
Classifier: Operating System :: OS Independent
Classifier: Programming Language :: Python
Classifier: Programming Language :: Python :: 3.10
Classifier: Programming Language :: Python :: 3.11
Classifier: Programming Language :: Python :: 3.12
Requires-Python: >=3.10
License-File: COPYING
Requires-Dist: h5py
Requires-Dist: igor2
Requires-Dist: loguru
Requires-Dist: matplotlib
Requires-Dist: pySPM
Requires-Dist: tifffile
Requires-Dist: ruamel.yaml
Provides-Extra: dev
Requires-Dist: black; extra == "dev"
Requires-Dist: pre-commit; extra == "dev"
Requires-Dist: pylint; extra == "dev"
Requires-Dist: pytest-testmon; extra == "dev"
Requires-Dist: ruff; extra == "dev"
Requires-Dist: setuptools_scm[toml]; extra == "dev"
Requires-Dist: wheel; extra == "dev"
Provides-Extra: docs
Requires-Dist: mike; extra == "docs"
Requires-Dist: mkdocs; extra == "docs"
Requires-Dist: mkdocs-material; extra == "docs"
Requires-Dist: mkdocs-mermaid2-plugin; extra == "docs"
Requires-Dist: mkdocs-terminal; extra == "docs"
Requires-Dist: mkdocstrings[python]; extra == "docs"
Provides-Extra: pypi
Requires-Dist: build; extra == "pypi"
Requires-Dist: setuptools_scm[toml]; extra == "pypi"
Requires-Dist: wheel; extra == "pypi"
Provides-Extra: tests
Requires-Dist: pytest; extra == "tests"
Requires-Dist: pytest-cov; extra == "tests"
Requires-Dist: pytest-loguru; extra == "tests"
Dynamic: license-file
